mr_plow-0.1.5.dist-info/DESCRIPTION.rst
mr_plow-0.1.5.dist-info/METADATA
mr_plow-0.1.5.dist-info/RECORD
mr_plow-0.1.5.dist-info/WHEEL
mr_plow-0.1.5.dist-info/entry_points.txt
mr_plow-0.1.5.dist-info/metadata.json
mr_plow-0.1.5.dist-info/top_level.txt
plow/__init__.py
plow/cli.py
plow/config.py
plow/op/__init__.py
plow/op/base.py
plow/op/etl.py
plow/op/extract.py
plow/op/staging.py
plow/queries/__init__.py
plow/queries/base.py
plow/queries/etl_tracking.py
plow/queries/livechat.py
plow/queries/snapfulfil.py
plow/queries/util.py
plow/testing/__init__.py
plow/testing/decimal_encoding.py
plow/vendors/__init__.py
plow/vendors/livechat.py
plow/vendors/snapfulfil.py
