Metadata-Version: 2.0
Name: mr-plow
Version: 0.1.5
Summary: ETL from third-party APIs into Snowflake
Home-page: https://github.com/Poppin-Tech/mr-plow
Author: Poppin
Author-email: technology@poppin.com
License: Apache
Keywords: Snowflake,Database,Amazon Web Services,AWS,S3,API,ETL
Platform: UNKNOWN
Classifier: Development Status :: 4 - Beta
Classifier: Environment :: Console
Classifier: Intended Audience :: Information Technology
Classifier: License :: OSI Approved :: Apache Software License
Classifier: Programming Language :: Python
Classifier: Programming Language :: Python :: 3
Classifier: Programming Language :: Python :: 3 :: Only
Classifier: Programming Language :: Python :: 3.6
Requires-Python: ~=3.6
Requires-Dist: boto3 (>=1.4.6)
Requires-Dist: click (>=6.7)
Requires-Dist: ijson (>=2.3)
Requires-Dist: requests (>=2.18.4)
Requires-Dist: snowflake-connector-python (>=1.4.10)
Requires-Dist: pyyaml (>=3.12)
Provides-Extra: dev
Requires-Dist: pytest; extra == 'dev'
Requires-Dist: pytest-cov; extra == 'dev'
Requires-Dist: pytest-mock; extra == 'dev'
Requires-Dist: flake8; extra == 'dev'
Requires-Dist: pytest-profiling; extra == 'dev'
